CHANGE LOG.txt
LICENCE.txt
MANIFEST.in
README.txt
setup.py
APL.egg-info/PKG-INFO
APL.egg-info/SOURCES.txt
APL.egg-info/dependency_links.txt
APL.egg-info/top_level.txt
APl/APL.py