Metadata-Version: 1.1
Name: APL
Version: 0.0.10
Summary: A library includes my important funcs
Home-page: https://www.youtube.com/channel/UCknfQGHQG0iXJVLOwijKdRA
Author: Ahmad Draie
Author-email: ahmaddraa2000@gmail.com
License: MIT
Keywords: a lot of things
Platform: UNKNOWN
Classifier: Development Status :: 5 - Production/Stable
Classifier: Intended Audience :: Education
Classifier: Operating System :: Microsoft :: Windows :: Windows 10
Classifier: License :: OSI Approved :: MIT License
Classifier: Programming Language :: Python :: 3
